das_utils/__init__.py
das_utils/config_util.py
das_utils/__pycache__/__init__.cpython-36.pyc
das_utils/__pycache__/config_util.cpython-36.pyc
das_utils-1.0.6.dist-info/METADATA
das_utils-1.0.6.dist-info/WHEEL
das_utils-1.0.6.dist-info/top_level.txt
das_utils-1.0.6.dist-info/RECORD
