Metadata-Version: 2.1
Name: das_utils
Version: 1.0.6
Summary: 大众云学工具箱
Home-page: UNKNOWN
Author: Jem
Author-email: tank94@163.com
License: UNKNOWN
Platform: UNKNOWN
